trading_kiwcomp_models/__init__.py
trading_kiwcomp_models/models_v1/__init__.py
trading_kiwcomp_models/models_v1/initial_db.py
trading_kiwcomp_models/models_v1/binance/__init__.py
trading_kiwcomp_models/models_v1/binance/data/BinanceFuturesCOINMExchangeInfoSymbol.py
trading_kiwcomp_models/models_v1/binance/data/BinanceFuturesCOINMKline.py
trading_kiwcomp_models/models_v1/binance/data/BinanceFuturesUSDTExchangeInfoSymbol.py
trading_kiwcomp_models/models_v1/binance/data/BinanceFuturesUSDTKline.py
trading_kiwcomp_models/models_v1/binance/data/BinanceSpotExchangeInfoSymbol.py
trading_kiwcomp_models/models_v1/binance/data/BinanceSpotKline.py
trading_kiwcomp_models/models_v1/binance/data/__init__.py
trading_kiwcomp_models/models_v1/binance/data/base.py
trading_kiwcomp_models/models_v1/binance/stream/BinanceStreamFuturesCOINMKline.py
trading_kiwcomp_models/models_v1/binance/stream/BinanceStreamFuturesCOINMMarkPriceUpdate.py
trading_kiwcomp_models/models_v1/binance/stream/BinanceStreamFuturesUSDTKline.py
trading_kiwcomp_models/models_v1/binance/stream/BinanceStreamFuturesUSDTMarkPriceUpdate.py
trading_kiwcomp_models/models_v1/binance/stream/BinanceStreamSpotKline.py
trading_kiwcomp_models/models_v1/binance/stream/__init__.py
trading_kiwcomp_models/models_v1/binance/stream/base.py
trading_kiwcomp_models/models_v2/__init__.py
trading_kiwcomp_models/models_v2/initial_db.py
trading_kiwcomp_models/models_v2/binance/__init__.py
trading_kiwcomp_models/models_v2/binance/data/BinanceFuturesCOINMExchangeInfoSymbol.py
trading_kiwcomp_models/models_v2/binance/data/BinanceFuturesCOINMKline.py
trading_kiwcomp_models/models_v2/binance/data/BinanceFuturesUSDTExchangeInfoSymbol.py
trading_kiwcomp_models/models_v2/binance/data/BinanceFuturesUSDTKline.py
trading_kiwcomp_models/models_v2/binance/data/BinanceSpotExchangeInfoSymbol.py
trading_kiwcomp_models/models_v2/binance/data/BinanceSpotKline.py
trading_kiwcomp_models/models_v2/binance/data/__init__.py
trading_kiwcomp_models-0.1.17.dist-info/METADATA
trading_kiwcomp_models-0.1.17.dist-info/WHEEL
trading_kiwcomp_models-0.1.17.dist-info/top_level.txt
trading_kiwcomp_models-0.1.17.dist-info/RECORD
