Metadata-Version: 2.4
Name: trading-kiwcomp-models
Version: 0.1.17
Summary: Trading data models (Binance, Kafka, Postgres) for KiwComp
Author-email: Kiw Company <kiw.share.resource@gmail.com>
License: MIT
Requires-Python: >=3.8
Requires-Dist: sqlalchemy
Requires-Dist: psycopg2-binary
Requires-Dist: pydantic
